img_src/__init__.py
img_src/_version.py
img_src/basesdk.py
img_src/httpclient.py
img_src/images.py
img_src/presets.py
img_src/py.typed
img_src/sdk.py
img_src/sdkconfiguration.py
img_src/settings.py
img_src/usage.py
img_src/_hooks/__init__.py
img_src/_hooks/registration.py
img_src/_hooks/sdkhooks.py
img_src/_hooks/types.py
img_src/errors/__init__.py
img_src/errors/errorresponse.py
img_src/errors/imgsrcdefaulterror.py
img_src/errors/imgsrcerror.py
img_src/errors/no_response_error.py
img_src/errors/responsevalidationerror.py
img_src/models/__init__.py
img_src/models/activesignedurl.py
img_src/models/availableformats.py
img_src/models/cdnurls.py
img_src/models/createpresetop.py
img_src/models/createpresetrequest.py
img_src/models/createsignedurlop.py
img_src/models/createsignedurlrequest.py
img_src/models/credits.py
img_src/models/currentperiod.py
img_src/models/deleteimageop.py
img_src/models/deleteimagepathop.py
img_src/models/deletepresetop.py
img_src/models/deletepresetresponse.py
img_src/models/deleteresponse.py
img_src/models/errordetail.py
img_src/models/folderitem.py
img_src/models/getimageop.py
img_src/models/getpresetop.py
img_src/models/getsettingsop.py
img_src/models/getusageop.py
img_src/models/hateoaslinks.py
img_src/models/httpmetadata.py
img_src/models/imagedimensions.py
img_src/models/imagelistitem.py
img_src/models/imagelistresponse.py
img_src/models/imagemetadata.py
img_src/models/listimagesop.py
img_src/models/listpresetsop.py
img_src/models/listpresetsresponse.py
img_src/models/metadataresponse.py
img_src/models/pathdeleteresponse.py
img_src/models/planlimits.py
img_src/models/preset.py
img_src/models/searchimagesop.py
img_src/models/searchresponse.py
img_src/models/searchresult.py
img_src/models/security.py
img_src/models/settingsresponse.py
img_src/models/settingsupdateresponse.py
img_src/models/signedurlresponse.py
img_src/models/updatepresetop.py
img_src/models/updatepresetrequest.py
img_src/models/updatesettingsop.py
img_src-0.2.0.dist-info/licenses/LICENSE
img_src-0.2.0.dist-info/METADATA
img_src-0.2.0.dist-info/WHEEL
img_src-0.2.0.dist-info/top_level.txt
img_src-0.2.0.dist-info/RECORD
