Metadata-Version: 2.4
Name: img-src
Version: 0.2.0
Summary: Official Python SDK for img-src.io - Developer-first image CDN
Author-email: Taehun <taehun@taehun.dev>
License: MIT
Requires-Python: >=3.9.2
License-File: LICENSE
Requires-Dist: httpcore>=1.0.9
Requires-Dist: httpx>=0.28.1
Requires-Dist: jsonpath-python>=1.0.6
Requires-Dist: pydantic>=2.11.2
Dynamic: license-file
